datasette_surveys
