Metadata-Version: 2.1
Name: datasette-surveys
Version: 1.1.6
Summary: Datasette plugin for creating surveys and collecting responses all in one place.
Home-page: https://github.com/next-LI/datasette-surveys
Author: Brandon Roberts
Author-email: brandon@bxroberts.org
License: Apache License, Version 2.0
Platform: UNKNOWN
Provides-Extra: test
